r614_o11y/__init__.py
r614_o11y/o11y.py
r614_o11y/py.typed
r614_o11y-0.1.6.dist-info/LICENSE
r614_o11y-0.1.6.dist-info/METADATA
r614_o11y-0.1.6.dist-info/WHEEL
r614_o11y-0.1.6.dist-info/RECORD
