Metadata-Version: 2.1
Name: r614-o11y
Version: 0.1.6
Summary: Observability modules
License: CC0 1.0
Author: Roshan Pawar
Author-email: steradian614@gmail.com
Requires-Python: >=3.11,<4.0
Classifier: License :: Other/Proprietary License
Classifier: Programming Language :: Python :: 3
Classifier: Programming Language :: Python :: 3.11
Requires-Dist: opentelemetry-api (>=1.15.0,<2.0.0)
Requires-Dist: opentelemetry-exporter-otlp-proto-grpc (>=1.15.0,<2.0.0)
Requires-Dist: opentelemetry-sdk (>=1.15.0,<2.0.0)
Requires-Dist: orjson (>=3.8.5,<4.0.0)
Requires-Dist: r614-config (>=0.1.7,<0.2.0)
Requires-Dist: structlog (>=22.3.0,<23.0.0)
